did_resolver/.DS_Store
did_resolver/__init__.py
did_resolver/resolver.py
did_resolver-0.0.3.dist-info/WHEEL
did_resolver-0.0.3.dist-info/METADATA
did_resolver-0.0.3.dist-info/RECORD
