Metadata-Version: 2.1
Name: did-resolver
Version: 0.0.3
License: MIT
Author-email: tintinthong <justin.thong@cardstack.com>
Requires-Python: >=3.9
Requires-Dist: typing-extensions>=4.3.0
